krk/__init__.py
krk/__main__.py
krk/cli.py
krk/krk.py
krk-0.0.1a0.dist-info/LICENSE
krk-0.0.1a0.dist-info/METADATA
krk-0.0.1a0.dist-info/WHEEL
krk-0.0.1a0.dist-info/entry_points.txt
krk-0.0.1a0.dist-info/top_level.txt
krk-0.0.1a0.dist-info/RECORD
