Metadata-Version: 2.1
Name: krk
Version: 0.0.1a0
Summary: A command-line utility for all krk projects
Home-page: https://github.com/krakakai/krk
Author: Stan Verschuuren
Author-email: delangstenerdopaarde@gmail.com
License: UNKNOWN
Project-URL: Bug Tracker, https://github.com/krakakai/krk/issues
Keywords: krk,robotics
Platform: UNKNOWN
Classifier: Development Status :: 1 - Planning
Classifier: Intended Audience :: Developers
Classifier: Programming Language :: Python :: 3
Classifier: Operating System :: Unix
Classifier: Operating System :: MacOS :: MacOS X
Classifier: Operating System :: Microsoft :: Windows
Requires-Python: >=3.6
License-File: LICENSE
Provides-Extra: test
Requires-Dist: coverage ; extra == 'test'
Requires-Dist: pytest ; extra == 'test'
Requires-Dist: pytest-cov ; extra == 'test'
